ml_anim/__init__.py
ml_anim/nn/__init__.py
ml_anim-0.0.1.dist-info/METADATA
ml_anim-0.0.1.dist-info/WHEEL
ml_anim-0.0.1.dist-info/top_level.txt
ml_anim-0.0.1.dist-info/RECORD
